Mailnag/__init__.py
Mailnag/backends/__init__.py
Mailnag/backends/base.py
Mailnag/backends/imap.py
Mailnag/backends/local.py
Mailnag/backends/pop3.py
Mailnag/common/__init__.py
Mailnag/common/accounts.py
Mailnag/common/config.py
Mailnag/common/dist_cfg.py
Mailnag/common/exceptions.py
Mailnag/common/i18n.py
Mailnag/common/imaplib2.py
Mailnag/common/mutf7.py
Mailnag/common/plugins.py
Mailnag/common/secretstore.py
Mailnag/common/subproc.py
Mailnag/common/utils.py
Mailnag/configuration/__init__.py
Mailnag/configuration/accountdialog.py
Mailnag/configuration/configwindow.py
Mailnag/configuration/plugindialog.py
Mailnag/configuration/desktop/__init__.py
Mailnag/configuration/desktop/mailnagger.desktop
Mailnag/configuration/ui/__init__.py
Mailnag/configuration/ui/account_widget.ui
Mailnag/configuration/ui/config_window.ui
Mailnag/daemon/__init__.py
Mailnag/daemon/conntest.py
Mailnag/daemon/dbus.py
Mailnag/daemon/idlers.py
Mailnag/daemon/mailchecker.py
Mailnag/daemon/mailnagdaemon.py
Mailnag/daemon/mails.py
Mailnag/plugins/libnotifyplugin.py
Mailnag/plugins/soundplugin.py
Mailnag/plugins/spamfilterplugin.py
Mailnag/plugins/userscriptplugin.py
mailnagger/__init__.py
mailnagger/__main__.py
mailnagger/resources.py
mailnagger/config/__init__.py
mailnagger/config/__main__.py
mailnagger/daemon/__init__.py
mailnagger-2.3.1.data/data/share/applications/mailnagger-config.desktop
mailnagger-2.3.1.data/data/share/applications/mailnagger.desktop
mailnagger-2.3.1.data/data/share/icons/hicolor/128x128/apps/mailnag.png
mailnagger-2.3.1.data/data/share/icons/hicolor/16x16/apps/mailnag.png
mailnagger-2.3.1.data/data/share/icons/hicolor/22x22/apps/mailnag.png
mailnagger-2.3.1.data/data/share/icons/hicolor/24x24/apps/mailnag.png
mailnagger-2.3.1.data/data/share/icons/hicolor/256x256/apps/mailnag.png
mailnagger-2.3.1.data/data/share/icons/hicolor/32x32/apps/mailnag.png
mailnagger-2.3.1.data/data/share/icons/hicolor/48x48/apps/mailnag.png
mailnagger-2.3.1.dist-info/LICENSE
mailnagger-2.3.1.dist-info/METADATA
mailnagger-2.3.1.dist-info/WHEEL
mailnagger-2.3.1.dist-info/entry_points.txt
mailnagger-2.3.1.dist-info/top_level.txt
mailnagger-2.3.1.dist-info/RECORD
