Metadata-Version: 2.1
Name: mailnagger
Version: 2.3.1
Summary: An extensible mail notification daemon
Author: Timo Kankare
Author-email: timo.kankare@iki.fi
License: GPL-2.0-or-later
Project-URL: homepage, https://github.com/tikank/mailnagger
Project-URL: source, https://github.com/tikank/mailnagger
Project-URL: issues, https://github.com/tikank/mailnagger/issues
Project-URL: releasenotes, https://github.com/tikank/mailnagger/blob/master/NEWS
Project-URL: documentation, https://github.com/tikank/mailnagger/tree/master/docs
Classifier: Development Status :: 5 - Production/Stable
Classifier: Environment :: X11 Applications
Classifier: Environment :: X11 Applications :: GTK
Classifier: Environment :: X11 Applications :: Gnome
Classifier: Intended Audience :: End Users/Desktop
Classifier: License :: OSI Approved :: GNU General Public License v2 or later (GPLv2+)
Classifier: Natural Language :: English
Classifier: Natural Language :: Finnish
Classifier: Natural Language :: German
Classifier: Operating System :: POSIX :: Linux
Classifier: Programming Language :: Python
Classifier: Programming Language :: Python :: 3
Classifier: Programming Language :: Python :: 3.9
Classifier: Programming Language :: Python :: 3.10
Classifier: Programming Language :: Python :: 3.11
Classifier: Programming Language :: Python :: 3.12
Classifier: Programming Language :: Python :: 3.13
Classifier: Topic :: Communications :: Email
Classifier: Topic :: Communications :: Email :: Post-Office :: IMAP
Classifier: Topic :: Communications :: Email :: Post-Office :: POP3
Classifier: Topic :: Utilities
Requires-Python: >=3.9
License-File: LICENSE
Requires-Dist: pygobject
Requires-Dist: pyxdg
Requires-Dist: dbus-python
Requires-Dist: importlib_resources; python_version < "3.11"
Provides-Extra: dev
Requires-Dist: pygobject-stubs; extra == "dev"
Requires-Dist: types-pyxdg; extra == "dev"
Requires-Dist: pytest; extra == "dev"
Requires-Dist: nox; extra == "dev"
Requires-Dist: types-setuptools; extra == "dev"
